jarplace-1.1.dist-info/DESCRIPTION.rst
jarplace-1.1.dist-info/METADATA
jarplace-1.1.dist-info/RECORD
jarplace-1.1.dist-info/WHEEL
jarplace-1.1.dist-info/entry_points.txt
jarplace-1.1.dist-info/metadata.json
jarplace-1.1.dist-info/top_level.txt
main/__init__.py
main/auth.py
main/billing.py
main/main.py
main/repo.py
main/user.py
