Metadata-Version: 2.0
Name: jarplace
Version: 1.1
Summary: CLI for JarPlace
Home-page: UNKNOWN
Author: UNKNOWN
Author-email: UNKNOWN
License: UNKNOWN
Platform: UNKNOWN
Requires-Python: >=3
Requires-Dist: requests
Requires-Dist: validate-email
